{"uniqueName":"IT:HeatExchanger","width":5,"height":3,"length":3,"master":{"x":2,"y":1,"z":0,"meta":0,"mod":"ore","name":"blockSheetmetalIron"},"pointsOfInterest":[{"name":"input1","position":5,"facing":4},{"name":"output1","position":9,"facing":5},{"name":"redstone","position":16,"facing":3},{"name":"output0","position":35,"facing":1},{"name":"energy","position":37,"facing":1},{"name":"input0","position":39,"facing":1},{"name":"sound","position":22,"facing":2}],"palette":[{"mod":"ore","name":"scaffoldingSteel","character":"S","meta":0},{"mod":"immersiveengineering","name":"metal_device1","character":"P","meta":6},{"mod":"ore","name":"blockSheetmetalIron","character":"I","meta":0},{"mod":"immersiveengineering","name":"metal_decoration0","character":"R","meta":3},{"mod":"immersiveengineering","name":"metal_decoration0","character":"L","meta":4},{"mod":"immersiveengineering","name":"metal_decoration0","character":"A","meta":7}],"structure":["SLSSS","PPPPP","SSSSS","IRIII","AAAAA","IIIII","ILIII","PPPPP","IIIII"],"AABB":[[[16,8,8,14,8,16],[16,4,0,8,8,16],[16,0,0,16,0,8]],[],[[16,4,0,16,8,16],[16,0,0,16,0,8]],[[16,4,0,16,8,16],[16,0,0,16,0,8]],[[8,4,8,16,8,16],[16,8,2,16,8,16],[16,0,0,16,0,8]],[[16,0,14,16,0,8],[16,0,0,14,0,16]],[],[],[],[[16,0,0,2,0,8],[16,0,2,16,0,16]],[[8,0,8,14,8,16],[12,0,0,8,8,16],[16,0,0,16,0,8]],[[12,0,0,16,8,16],[16,0,0,16,0,8]],[[12,0,0,16,8,16],[16,0,0,16,0,8]],[[12,0,0,16,8,16],[16,0,0,16,0,8]],[[8,0,2,8,8,16],[12,0,8,16,8,16],[16,0,0,16,0,8]],[[16,8,8,14,0,16],[16,4,0,8,0,16]],[],[[16,4,0,16,0,16]],[[16,4,0,16,0,16]],[[8,4,8,16,0,16],[16,8,2,16,0,16]],[[16,0,0,14,0,16]],[],[],[],[[16,0,2,16,0,16]],[[8,0,8,14,0,16],[12,0,0,8,0,16]],[[12,0,0,16,0,16]],[[12,0,0,16,0,16]],[[12,0,0,16,0,16]],[[8,0,2,8,0,16],[12,0,8,16,0,16]],[[16,10,0,8,10,16],[16,8,8,14,0,8],[16,4,0,8,0,10]],[],[[16,10,0,16,10,16],[16,4,0,16,0,10]],[[16,10,0,16,10,16],[16,4,0,16,0,10]],[[16,4,8,16,8,10],[16,10,8,16,10,16],[8,4,8,16,0,8],[16,8,2,16,0,8]],[[16,0,14,16,8,16],[16,0,0,14,0,16]],[],[],[],[[16,0,0,2,8,16],[16,0,2,16,0,16]],[[6,0,0,8,10,16],[8,0,8,14,0,8],[12,0,0,8,0,10]],[[6,0,0,16,10,16],[12,0,0,16,0,10]],[[6,0,0,16,10,16],[12,0,0,16,0,10]],[[6,0,0,16,10,16],[12,0,0,16,0,10]],[[6,0,8,16,10,16],[8,0,2,8,0,8],[12,0,8,16,0,10]]]}